[
       {
              "Position": 1,
              "name": "\n\t\t\t\t\t\tE-commerce site\n\t\t\t\t\t",
              "link": "/test-sites/e-commerce/allinone"
       },
       {
              "Position": 2,
              "name": "\n\t\t\t\t\t\tE-commerce site with pagination links\n\t\t\t\t\t",
              "link": "/test-sites/e-commerce/static"
       },
       {
              "Position": 3,
              "name": "\n\t\t\t\t\t\tE-commerce site with popup links\n\t\t\t\t\t",
              "link": "/test-sites/e-commerce/allinone-popup-links"
       },
       {
              "Position": 4,
              "name": "\n\t\t\t\t\t\tE-commerce site with AJAX pagination links\n\t\t\t\t\t",
              "link": "/test-sites/e-commerce/ajax"
       },
       {
              "Position": 5,
              "name": "\n\t\t\t\t\t\tE-commerce site with \"Load more\" buttons\n\t\t\t\t\t",
              "link": "/test-sites/e-commerce/more"
       },
       {
              "Position": 6,
              "name": "\n\t\t\t\t\t\tE-commerce site that loads items while scrolling\n\t\t\t\t\t",
              "link": "/test-sites/e-commerce/scroll"
       },
       {
              "Position": 7,
              "name": "Table playground\n\t\t\t\t\t",
              "link": "/test-sites/tables"
       }
]